ProbabPyReason/__init__.py
ProbabPyReason/HiddenMarkovModel.py
ProbabPyReason-0.1.3.dist-info/DESCRIPTION.rst
ProbabPyReason-0.1.3.dist-info/METADATA
ProbabPyReason-0.1.3.dist-info/metadata.json
ProbabPyReason-0.1.3.dist-info/RECORD
ProbabPyReason-0.1.3.dist-info/top_level.txt
ProbabPyReason-0.1.3.dist-info/WHEEL
