Metadata-Version: 2.0
Name: ProbabPyReason
Version: 0.1.3
Summary: Probabilistic Reasoning
Home-page: https://github.com/MBALearnsToCode/ProbabPyReason
Author: Vinh Luong (a.k.a. MBALearnsToCode)
Author-email: MBALearnsToCode@UChicago.edu
License: MIT License
Keywords: prob probability reasoning
Platform: UNKNOWN
Requires-Dist: FrozenDict
Requires-Dist: ProbabPy
